grpc_argument_validator/__init__.py
grpc_argument_validator/argument_validator_config.py
grpc_argument_validator/argument_validators.py
grpc_argument_validator/fields.py
grpc_argument_validator/py.typed
grpc_argument_validator/validate_args_decorator.py
grpc_argument_validator/validation_context.py
grpc_argument_validator/validation_result.py
grpc_argument_validator-0.2.2.dist-info/LICENSE
grpc_argument_validator-0.2.2.dist-info/WHEEL
grpc_argument_validator-0.2.2.dist-info/METADATA
grpc_argument_validator-0.2.2.dist-info/RECORD
