Metadata-Version: 2.1
Name: grpc-argument-validator
Version: 0.2.2
Summary: gRPC argument validator utility.
Home-page: https://github.com/messagebird/python-grpc-argument-validator
License: BSD 3-Clause
Author: Jos van de Wolfshaar
Author-email: jos@messagebird.com
Requires-Python: >=3.7,<4.0
Classifier: License :: Other/Proprietary License
Classifier: Programming Language :: Python :: 3
Classifier: Programming Language :: Python :: 3.10
Classifier: Programming Language :: Python :: 3.7
Classifier: Programming Language :: Python :: 3.8
Classifier: Programming Language :: Python :: 3.9
Requires-Dist: grpcio
Requires-Dist: grpcio-status
Requires-Dist: protobuf
Project-URL: Documentation, https://messagebird.github.io/python-grpc-argument-validator
Project-URL: Repository, https://github.com/messagebird/python-grpc-argument-validator
